rotest_reportportal/__init__.py
rotest_reportportal-2.0.1.dist-info/METADATA
rotest_reportportal-2.0.1.dist-info/WHEEL
rotest_reportportal-2.0.1.dist-info/entry_points.txt
rotest_reportportal-2.0.1.dist-info/top_level.txt
rotest_reportportal-2.0.1.dist-info/RECORD
