Metadata-Version: 2.1
Name: rotest-reportportal
Version: 2.0.1
Summary: Rotest result handler to send data to a ReportPortal system
Home-page: https://github.com/gregoil/rotest_reportportal
Author: gregoil
Author-email: gregoil@walla.co.il
License: MIT
Keywords: testing system reportportal unittest
Platform: UNKNOWN
Requires-Python: >=2.7,!=3.0.*,!=3.1.*,!=3.2.*,!=3.3.*,!=3.4.*,<3.8.0
Requires-Dist: rotest
Requires-Dist: attrdict
Requires-Dist: pyyaml
Requires-Dist: reportportal-client
Provides-Extra: dev
Requires-Dist: flake8 ; extra == 'dev'
Requires-Dist: pylint ; extra == 'dev'
Requires-Dist: pytest ; extra == 'dev'
Requires-Dist: pytest-cov ; extra == 'dev'
Requires-Dist: mock ; extra == 'dev'
